{
  "驱动": {
    "ru": "драйвер",
    "en": "driver",
    "note": "программное обеспечение для управления аппаратными устройствами"
  },
  "驱动开发": {
    "ru": "разработка драйверов",
    "en": "driver development",
    "note": "процесс создания драйверов для устройств"
  },
  "应用": {
    "ru": "приложение",
    "en": "application",
    "note": "прикладное программное обеспечение"
  },
  "应用开发": {
    "ru": "разработка приложений",
    "en": "application development",
    "note": "процесс создания пользовательских приложений"
  },
  "系统": {
    "ru": "система",
    "en": "system",
    "note": "операционная система"
  },
  "系统软件": {
    "ru": "системное программное обеспечение",
    "en": "system software",
    "note": "базовое ПО для работы системы"
  },
  "开发": {
    "ru": "разработка",
    "en": "development",
    "note": "процесс создания программного обеспечения"
  },
  "开发板": {
    "ru": "отладочная плата",
    "en": "development board",
    "note": "плата для разработки и тестирования"
  },
  "编译": {
    "ru": "компиляция",
    "en": "compilation",
    "note": "процесс преобразования исходного кода в исполняемый файл"
  },
  "交叉编译": {
    "ru": "кросс-компиляция",
    "en": "cross-compilation",
    "note": "компиляция для другой платформы"
  },
  "配置": {
    "ru": "конфигурация",
    "en": "configuration",
    "note": "настройка параметров системы"
  },
  "内核": {
    "ru": "ядро",
    "en": "kernel",
    "note": "ядро операционной системы Linux"
  },
  "引脚": {
    "ru": "вывод, пин",
    "en": "pin",
    "note": "физический контакт микросхемы"
  },
  "管脚": {
    "ru": "вывод",
    "en": "pin",
    "note": "контакт микросхемы"
  },
  "引脚复用": {
    "ru": "мультиплексирование выводов",
    "en": "pin multiplexing, pinmux",
    "note": "использование одного вывода для нескольких функций"
  },
  "上拉": {
    "ru": "подтяжка к питанию",
    "en": "pull-up",
    "note": "подключение резистора к питанию"
  },
  "下拉": {
    "ru": "подтяжка к земле",
    "en": "pull-down",
    "note": "подключение резистора к земле"
  },
  "驱动能力": {
    "ru": "способность управления нагрузкой",
    "en": "drive strength",
    "note": "сила тока, которую может обеспечить вывод"
  },
  "输入": {
    "ru": "вход",
    "en": "input",
    "note": "режим работы вывода на вход"
  },
  "输出": {
    "ru": "выход",
    "en": "output",
    "note": "режим работы вывода на выход"
  },
  "中断": {
    "ru": "прерывание",
    "en": "interrupt",
    "note": "сигнал для немедленной обработки события"
  },
  "设备树": {
    "ru": "дерево устройств",
    "en": "device tree",
    "note": "структура данных для описания аппаратной конфигурации"
  },
  "固件": {
    "ru": "прошивка",
    "en": "firmware",
    "note": "программное обеспечение, записанное в устройство"
  },
  "烧录": {
    "ru": "прошивка, запись",
    "en": "flashing",
    "note": "процесс записи образа в память устройства"
  },
  "烧写": {
    "ru": "запись",
    "en": "programming, flashing",
    "note": "процесс записи данных в память"
  },
  "镜像": {
    "ru": "образ",
    "en": "image",
    "note": "файл образа системы для записи"
  },
  "分区": {
    "ru": "раздел",
    "en": "partition",
    "note": "логический раздел памяти"
  },
  "挂载": {
    "ru": "монтирование",
    "en": "mounting",
    "note": "подключение файловой системы"
  },
  "根文件系统": {
    "ru": "корневая файловая система",
    "en": "root filesystem",
    "note": "основная файловая система"
  },
  "文件系统": {
    "ru": "файловая система",
    "en": "filesystem",
    "note": "система организации данных на носителе"
  },
  "打包": {
    "ru": "упаковка",
    "en": "packing",
    "note": "создание итогового образа системы"
  },
  "启动": {
    "ru": "загрузка",
    "en": "boot",
    "note": "процесс запуска системы"
  },
  "引导": {
    "ru": "загрузка",
    "en": "boot",
    "note": "процесс инициализации системы"
  },
  "引导程序": {
    "ru": "загрузчик",
    "en": "bootloader",
    "note": "программа начальной загрузки"
  },
  "设备节点": {
    "ru": "узел устройства",
    "en": "device node",
    "note": "файл, представляющий устройство в /dev"
  },
  "事件": {
    "ru": "событие",
    "en": "event",
    "note": "входное событие от устройства"
  },
  "输入系统": {
    "ru": "система ввода",
    "en": "input system",
    "note": "подсистема обработки устройств ввода"
  },
  "输入设备": {
    "ru": "устройство ввода",
    "en": "input device",
    "note": "устройство для ввода данных"
  },
  "键盘": {
    "ru": "клавиатура",
    "en": "keyboard",
    "note": "устройство ввода с клавишами"
  },
  "鼠标": {
    "ru": "мышь",
    "en": "mouse",
    "note": "манипулятор"
  },
  "触摸屏": {
    "ru": "сенсорный экран",
    "en": "touchscreen",
    "note": "устройство ввода касанием"
  },
  "按键": {
    "ru": "клавиша, кнопка",
    "en": "key, button",
    "note": "элемент ввода"
  },
  "坐标": {
    "ru": "координаты",
    "en": "coordinates",
    "note": "позиция на экране или поверхности"
  },
  "绝对事件": {
    "ru": "абсолютное событие",
    "en": "absolute event",
    "note": "событие с абсолютными координатами"
  },
  "相对事件": {
    "ru": "относительное событие",
    "en": "relative event",
    "note": "событие с относительным смещением"
  },
  "按键事件": {
    "ru": "событие клавиши",
    "en": "key event",
    "note": "событие нажатия или отпускания клавиши"
  },
  "同步事件": {
    "ru": "событие синхронизации",
    "en": "sync event",
    "note": "событие разделения пакетов событий"
  },
  "寄存器": {
    "ru": "регистр",
    "en": "register",
    "note": "регистр процессора или периферии"
  },
  "总线": {
    "ru": "шина",
    "en": "bus",
    "note": "канал передачи данных"
  },
  "串口": {
    "ru": "последовательный порт",
    "en": "serial port, UART",
    "note": "интерфейс последовательной передачи данных"
  },
  "控制器": {
    "ru": "контроллер",
    "en": "controller",
    "note": "управляющее устройство"
  },
  "软件包": {
    "ru": "пакет",
    "en": "package",
    "note": "программный пакет"
  },
  "工具链": {
    "ru": "цепочка инструментов",
    "en": "toolchain",
    "note": "набор инструментов для разработки"
  },
  "源码": {
    "ru": "исходный код",
    "en": "source code",
    "note": "исходные тексты программ"
  },
  "调试": {
    "ru": "отладка",
    "en": "debugging",
    "note": "процесс поиска и исправления ошибок"
  },
  "模块": {
    "ru": "модуль",
    "en": "module",
    "note": "программный или аппаратный модуль"
  },
  "框架": {
    "ru": "фреймворк",
    "en": "framework",
    "note": "программная платформа"
  },
  "接口": {
    "ru": "интерфейс",
    "en": "interface",
    "note": "точка взаимодействия"
  },
  "方案": {
    "ru": "решение, конфигурация",
    "en": "solution, board configuration",
    "note": "конфигурация для конкретной платы"
  },
  "平台": {
    "ru": "платформа",
    "en": "platform",
    "note": "аппаратная или программная платформа"
  },
  "芯片": {
    "ru": "чип, микросхема",
    "en": "chip, SoC",
    "note": "интегральная схема"
  },
  "处理器": {
    "ru": "процессор",
    "en": "processor, CPU",
    "note": "центральный процессор"
  },
  "存储": {
    "ru": "хранение, память",
    "en": "storage, memory",
    "note": "устройство хранения данных"
  },
  "闪存": {
    "ru": "флеш-память",
    "en": "flash memory",
    "note": "энергонезависимая память"
  },
  "内存": {
    "ru": "оперативная память",
    "en": "RAM, memory",
    "note": "оперативная память"
  },
  "100ASK_T113-Pro开发板": {
    "ru": "отладочная плата 100ASK T113-Pro",
    "en": "100ASK T113-Pro development board",
    "note": "отладочная плата на базе процессора T113"
  },
  "D1-H东山哪吒STU开发板": {
    "ru": "отладочная плата Dongshan Nezha D1-H STU",
    "en": "Dongshan Nezha D1-H STU development board",
    "note": "отладочная плата на базе процессора D1-H"
  },
  "DongshanPI-D1s开发板": {
    "ru": "отладочная плата DongshanPI D1s",
    "en": "DongshanPI D1s development board",
    "note": "отладочная плата на базе процессора D1s"
  },
  "100ASK_V853-PRO开发板": {
    "ru": "отладочная плата 100ASK V853-PRO",
    "en": "100ASK V853-PRO development board",
    "note": "отладочная плата на базе процессора V853"
  },
  "柚木PI-Lizard": {
    "ru": "отладочная плата Youmu PI-Lizard",
    "en": "Youmu PI-Lizard board",
    "note": "отладочная плата на базе V851s"
  },
  "全志": {
    "ru": "Allwinner",
    "en": "Allwinner",
    "note": "компания-производитель процессоров"
  },
  "百问网": {
    "ru": "100ask",
    "en": "100ask",
    "note": "образовательная платформа"
  },
  "外设": {
    "ru": "периферия",
    "en": "peripheral",
    "note": "периферийное устройство"
  },
  "电源": {
    "ru": "питание",
    "en": "power",
    "note": "источник питания"
  },
  "电压": {
    "ru": "напряжение",
    "en": "voltage",
    "note": "электрическое напряжение"
  },
  "电平": {
    "ru": "уровень",
    "en": "level",
    "note": "логический уровень сигнала"
  },
  "高电平": {
    "ru": "высокий уровень",
    "en": "high level",
    "note": "логическая единица"
  },
  "低电平": {
    "ru": "низкий уровень",
    "en": "low level",
    "note": "логический ноль"
  },
  "触发": {
    "ru": "срабатывание",
    "en": "trigger",
    "note": "активация события"
  },
  "复位": {
    "ru": "сброс",
    "en": "reset",
    "note": "возврат в исходное состояние"
  },
  "时钟": {
    "ru": "тактовый сигнал",
    "en": "clock",
    "note": "синхронизирующий сигнал"
  },
  "频率": {
    "ru": "частота",
    "en": "frequency",
    "note": "частота сигнала"
  },
  "波特率": {
    "ru": "скорость передачи",
    "en": "baud rate",
    "note": "скорость передачи данных"
  },
  "传输": {
    "ru": "передача",
    "en": "transmission",
    "note": "передача данных"
  },
  "接收": {
    "ru": "прием",
    "en": "reception, receive",
    "note": "прием данных"
  },
  "发送": {
    "ru": "передача",
    "en": "transmission, send",
    "note": "отправка данных"
  },
  "数据": {
    "ru": "данные",
    "en": "data",
    "note": "информация"
  },
  "缓冲": {
    "ru": "буфер",
    "en": "buffer",
    "note": "временное хранилище данных"
  },
  "队列": {
    "ru": "очередь",
    "en": "queue",
    "note": "структура данных FIFO"
  },
  "状态": {
    "ru": "состояние",
    "en": "state, status",
    "note": "текущее состояние"
  },
  "错误": {
    "ru": "ошибка",
    "en": "error",
    "note": "сбой или ошибка"
  },
  "超时": {
    "ru": "таймаут",
    "en": "timeout",
    "note": "превышение времени ожидания"
  },
  "延迟": {
    "ru": "задержка",
    "en": "delay",
    "note": "временная задержка"
  },
  "休眠": {
    "ru": "сон, спящий режим",
    "en": "sleep, suspend",
    "note": "режим пониженного энергопотребления"
  },
  "唤醒": {
    "ru": "пробуждение",
    "en": "wake up",
    "note": "выход из спящего режима"
  },
  "功耗": {
    "ru": "энергопотребление",
    "en": "power consumption",
    "note": "потребляемая мощность"
  },
  "环境变量": {
    "ru": "переменная окружения",
    "en": "environment variable",
    "note": "системная переменная"
  },
  "命令": {
    "ru": "команда",
    "en": "command",
    "note": "команда системы или программы"
  },
  "脚本": {
    "ru": "скрипт",
    "en": "script",
    "note": "программный сценарий"
  },
  "库": {
    "ru": "библиотека",
    "en": "library",
    "note": "программная библиотека"
  },
  "依赖": {
    "ru": "зависимость",
    "en": "dependency",
    "note": "требуемый компонент"
  },
  "路径": {
    "ru": "путь",
    "en": "path",
    "note": "путь к файлу или директории"
  },
  "目录": {
    "ru": "директория, каталог",
    "en": "directory",
    "note": "папка файловой системы"
  },
  "文件": {
    "ru": "файл",
    "en": "file",
    "note": "файл данных"
  },
  "权限": {
    "ru": "права доступа",
    "en": "permissions",
    "note": "права на файл или ресурс"
  },
  "用户": {
    "ru": "пользователь",
    "en": "user",
    "note": "пользователь системы"
  },
  "用户空间": {
    "ru": "пространство пользователя",
    "en": "user space",
    "note": "область памяти приложений"
  },
  "内核空间": {
    "ru": "пространство ядра",
    "en": "kernel space",
    "note": "область памяти ядра"
  },
  "进程": {
    "ru": "процесс",
    "en": "process",
    "note": "выполняющаяся программа"
  },
  "线程": {
    "ru": "поток",
    "en": "thread",
    "note": "поток выполнения"
  },
  "服务": {
    "ru": "служба, сервис",
    "en": "service",
    "note": "фоновый процесс"
  },
  "守护进程": {
    "ru": "демон",
    "en": "daemon",
    "note": "фоновая служба"
  },
  "日志": {
    "ru": "журнал, лог",
    "en": "log",
    "note": "файл регистрации событий"
  },
  "升级": {
    "ru": "обновление",
    "en": "upgrade",
    "note": "обновление ПО"
  },
  "版本": {
    "ru": "версия",
    "en": "version",
    "note": "версия ПО"
  },
  "补丁": {
    "ru": "патч",
    "en": "patch",
    "note": "исправление кода"
  },
  "安装": {
    "ru": "установка",
    "en": "installation",
    "note": "установка ПО"
  },
  "卸载": {
    "ru": "удаление",
    "en": "uninstallation",
    "note": "удаление ПО"
  },
  "测试": {
    "ru": "тестирование",
    "en": "testing",
    "note": "проверка работоспособности"
  },
  "示例": {
    "ru": "пример",
    "en": "example",
    "note": "пример кода или использования"
  },
  "文档": {
    "ru": "документация",
    "en": "documentation",
    "note": "техническая документация"
  },
  "指南": {
    "ru": "руководство",
    "en": "guide",
    "note": "руководство пользователя"
  },
  "手册": {
    "ru": "справочник",
    "en": "manual",
    "note": "справочное руководство"
  },
  "网络": {
    "ru": "сеть",
    "en": "network",
    "note": "компьютерная сеть"
  },
  "通信": {
    "ru": "связь, коммуникация",
    "en": "communication",
    "note": "обмен данными"
  },
  "协议": {
    "ru": "протокол",
    "en": "protocol",
    "note": "сетевой или интерфейсный протокол"
  },
  "显示": {
    "ru": "отображение, дисплей",
    "en": "display",
    "note": "вывод информации"
  },
  "屏幕": {
    "ru": "экран",
    "en": "screen",
    "note": "устройство отображения"
  },
  "界面": {
    "ru": "интерфейс",
    "en": "interface, UI",
    "note": "пользовательский интерфейс"
  },
  "多媒体": {
    "ru": "мультимедиа",
    "en": "multimedia",
    "note": "аудио и видео"
  },
  "音频": {
    "ru": "аудио",
    "en": "audio",
    "note": "звук"
  },
  "视频": {
    "ru": "видео",
    "en": "video",
    "note": "видеоизображение"
  },
  "摄像头": {
    "ru": "камера",
    "en": "camera",
    "note": "устройство захвата видео"
  },
  "传感器": {
    "ru": "датчик, сенсор",
    "en": "sensor",
    "note": "измерительное устройство"
  },
  "电机": {
    "ru": "двигатель",
    "en": "motor",
    "note": "электродвигатель"
  },
  "舵机": {
    "ru": "сервопривод",
    "en": "servo",
    "note": "сервомотор"
  },
  "继电器": {
    "ru": "реле",
    "en": "relay",
    "note": "электромеханическое реле"
  },
  "开关": {
    "ru": "переключатель",
    "en": "switch",
    "note": "коммутационное устройство"
  },
  "按钮": {
    "ru": "кнопка",
    "en": "button",
    "note": "элемент управления"
  },
  "指示灯": {
    "ru": "индикатор",
    "en": "indicator LED",
    "note": "светодиодный индикатор"
  },
  "充电": {
    "ru": "зарядка",
    "en": "charging",
    "note": "процесс зарядки батареи"
  },
  "电池": {
    "ru": "батарея",
    "en": "battery",
    "note": "источник питания"
  },
  "量产": {
    "ru": "массовое производство",
    "en": "mass production",
    "note": "серийное производство"
  },
  "仓库": {
    "ru": "репозиторий",
    "en": "repository",
    "note": "хранилище кода"
  },
  "提交": {
    "ru": "коммит",
    "en": "commit",
    "note": "фиксация изменений"
  },
  "分支": {
    "ru": "ветка",
    "en": "branch",
    "note": "ветка разработки"
  },
  "合并": {
    "ru": "слияние",
    "en": "merge",
    "note": "объединение изменений"
  },
  "克隆": {
    "ru": "клонирование",
    "en": "clone",
    "note": "копирование репозитория"
  },
  "推送": {
    "ru": "отправка",
    "en": "push",
    "note": "отправка изменений в репозиторий"
  },
  "拉取": {
    "ru": "получение",
    "en": "pull",
    "note": "получение изменений из репозитория"
  },
  "更新": {
    "ru": "обновление",
    "en": "update",
    "note": "обновление версии"
  },
  "同步": {
    "ru": "синхронизация",
    "en": "synchronization",
    "note": "синхронизация данных"
  },
  "备份": {
    "ru": "резервное копирование",
    "en": "backup",
    "note": "создание резервной копии"
  },
  "恢复": {
    "ru": "восстановление",
    "en": "recovery, restore",
    "note": "восстановление данных"
  },
  "格式化": {
    "ru": "форматирование",
    "en": "formatting",
    "note": "подготовка носителя"
  },
  "擦除": {
    "ru": "стирание",
    "en": "erase",
    "note": "удаление данных"
  },
  "读取": {
    "ru": "чтение",
    "en": "read",
    "note": "чтение данных"
  },
  "写入": {
    "ru": "запись",
    "en": "write",
    "note": "запись данных"
  },
  "清空": {
    "ru": "очистка",
    "en": "clear",
    "note": "удаление содержимого"
  },
  "运行": {
    "ru": "выполнение",
    "en": "run, execution",
    "note": "запуск программы"
  },
  "停止": {
    "ru": "остановка",
    "en": "stop",
    "note": "прекращение выполнения"
  },
  "重启": {
    "ru": "перезагрузка",
    "en": "reboot, restart",
    "note": "перезапуск системы"
  },
  "关机": {
    "ru": "выключение",
    "en": "shutdown, power off",
    "note": "выключение устройства"
  },
  "开机": {
    "ru": "включение",
    "en": "power on, boot",
    "note": "включение устройства"
  },
  "SDK": {
    "ru": "SDK, комплект для разработки",
    "en": "SDK, Software Development Kit",
    "note": "набор инструментов для разработки ПО"
  },
  "GPIO": {
    "ru": "GPIO",
    "en": "GPIO, General Purpose Input/Output",
    "note": "порт ввода-вывода общего назначения"
  },
  "PWM": {
    "ru": "ШИМ, PWM",
    "en": "PWM, Pulse Width Modulation",
    "note": "широтно-импульсная модуляция"
  },
  "I2C": {
    "ru": "I2C",
    "en": "I2C, Inter-Integrated Circuit",
    "note": "последовательная шина связи"
  },
  "SPI": {
    "ru": "SPI",
    "en": "SPI, Serial Peripheral Interface",
    "note": "последовательный периферийный интерфейс"
  },
  "UART": {
    "ru": "UART",
    "en": "UART, Universal Asynchronous Receiver/Transmitter",
    "note": "универсальный асинхронный приемопередатчик"
  },
  "USB": {
    "ru": "USB",
    "en": "USB, Universal Serial Bus",
    "note": "универсальная последовательная шина"
  },
  "HDMI": {
    "ru": "HDMI",
    "en": "HDMI, High-Definition Multimedia Interface",
    "note": "интерфейс мультимедиа высокой четкости"
  },
  "MIPI": {
    "ru": "MIPI",
    "en": "MIPI, Mobile Industry Processor Interface",
    "note": "интерфейс для мобильных процессоров"
  },
  "LCD": {
    "ru": "ЖК-дисплей",
    "en": "LCD, Liquid Crystal Display",
    "note": "жидкокристаллический дисплей"
  },
  "LED": {
    "ru": "светодиод",
    "en": "LED, Light-Emitting Diode",
    "note": "светоизлучающий диод"
  },
  "ADC": {
    "ru": "АЦП",
    "en": "ADC, Analog-to-Digital Converter",
    "note": "аналого-цифровой преобразователь"
  },
  "DAC": {
    "ru": "ЦАП",
    "en": "DAC, Digital-to-Analog Converter",
    "note": "цифро-аналоговый преобразователь"
  },
  "DMA": {
    "ru": "ПДП, DMA",
    "en": "DMA, Direct Memory Access",
    "note": "прямой доступ к памяти"
  },
  "RTC": {
    "ru": "часы реального времени",
    "en": "RTC, Real-Time Clock",
    "note": "часы реального времени"
  },
  "WDT": {
    "ru": "сторожевой таймер",
    "en": "WDT, Watchdog Timer",
    "note": "таймер наблюдения"
  },
  "MMC": {
    "ru": "MMC",
    "en": "MMC, MultiMediaCard",
    "note": "стандарт карт памяти"
  },
  "SD": {
    "ru": "SD-карта",
    "en": "SD card, Secure Digital card",
    "note": "карта защищенной цифровой памяти"
  },
  "TF": {
    "ru": "TF-карта, microSD",
    "en": "TF card, TransFlash card",
    "note": "карта памяти microSD"
  },
  "NAND": {
    "ru": "NAND флеш",
    "en": "NAND flash",
    "note": "тип флеш-памяти"
  },
  "NOR": {
    "ru": "NOR флеш",
    "en": "NOR flash",
    "note": "тип флеш-памяти"
  },
  "eMMC": {
    "ru": "eMMC",
    "en": "eMMC, embedded MultiMediaCard",
    "note": "встроенная флеш-память"
  },
  "DRAM": {
    "ru": "DRAM",
    "en": "DRAM, Dynamic RAM",
    "note": "динамическая оперативная память"
  },
  "DDR": {
    "ru": "DDR",
    "en": "DDR, Double Data Rate",
    "note": "память с удвоенной скоростью передачи"
  },
  "OTA": {
    "ru": "OTA, обновление по воздуху",
    "en": "OTA, Over-The-Air",
    "note": "беспроводное обновление ПО"
  },
  "ADB": {
    "ru": "ADB",
    "en": "ADB, Android Debug Bridge",
    "note": "мост отладки Android"
  },
  "Fastboot": {
    "ru": "Fastboot",
    "en": "Fastboot",
    "note": "протокол быстрой загрузки"
  }
}
